pyv6m/__init__.py
pyv6m/pyv6m.py
pyv6m/test.py
pyv6m/v6m.py
pyv6m/v6mrelay.py
pyv6m/v6msensor.py
pyv6m-0.0.1.dist-info/LICENSE
pyv6m-0.0.1.dist-info/METADATA
pyv6m-0.0.1.dist-info/WHEEL
pyv6m-0.0.1.dist-info/top_level.txt
pyv6m-0.0.1.dist-info/RECORD
