Metadata-Version: 2.1
Name: pyv6m
Version: 0.0.1
Summary: V6M relay controller over Ethernet
Home-page: https://github.com/dubnom/pyv6m
Author: Michael Dubno
Author-email: michael@dubno.com
License: UNKNOWN
Platform: UNKNOWN
Classifier: Programming Language :: Python :: 3
Classifier: License :: OSI Approved :: MIT License
Classifier: Operating System :: OS Independent
